Metadata-Version: 1.1
Name: termify
Version: 1.0.1
Summary: Termify is a simple service that permits you to retrieve lyrics in your terminal
Home-page: https://github.com/tiagobarreto/termify
Author: Tiago Barreto
Author-email: iam@tiagobarreto.com
License: MIT
Keywords: termify lyrics spotify terminal
Platform: UNKNOWN
Classifier: Development Status :: 3 - Alpha
Classifier: Topic :: Multimedia :: Sound/Audio :: Analysis
Classifier: License :: OSI Approved :: MIT License
Classifier: Programming Language :: Python :: 2
Classifier: Programming Language :: Python :: 2.6
Classifier: Programming Language :: Python :: 2.7
Classifier: Programming Language :: Python :: 3
Classifier: Programming Language :: Python :: 3.2
Classifier: Programming Language :: Python :: 3.3
Classifier: Programming Language :: Python :: 3.4
